lp_plotter/__init__.py
lp_plotter/parser.py
lp_plotter/plotter.py
lp_plotter-0.1.3.dist-info/licenses/LICENSE
lp_plotter-0.1.3.dist-info/METADATA
lp_plotter-0.1.3.dist-info/WHEEL
lp_plotter-0.1.3.dist-info/top_level.txt
lp_plotter-0.1.3.dist-info/RECORD
